laia_ontology_sync/__init__.py
laia_ontology_sync/config.py
laia_ontology_sync/fuseki_client.py
laia_ontology_sync/logger.py
laia_ontology_sync/rdf_mapper.py
laia_ontology_sync/watcher.py
laia_ontology_sync-0.1.2.dist-info/licenses/LICENSE
laia_ontology_sync-0.1.2.dist-info/METADATA
laia_ontology_sync-0.1.2.dist-info/WHEEL
laia_ontology_sync-0.1.2.dist-info/top_level.txt
laia_ontology_sync-0.1.2.dist-info/RECORD
