Metadata-Version: 2.4
Name: laia-ontology-sync
Version: 0.1.2
Summary: Librería para sincronizar MongoDB con Apache Jena Fuseki usando RDF.
Author: Itziar Mensa Minguito
Author-email: itziar.mensa08@gmail.com
Classifier: Programming Language :: Python :: 3
Classifier: License :: OSI Approved :: MIT License
Classifier: Operating System :: OS Independent
Requires-Python: >=3.9
License-File: LICENSE
Requires-Dist: requests>=2.0
Requires-Dist: rdflib>=7.0
Requires-Dist: pymongo>=4.0
Requires-Dist: python-dotenv>=1.0
Provides-Extra: dev
Requires-Dist: pytest; extra == "dev"
Requires-Dist: pytest-runner; extra == "dev"
Requires-Dist: setuptools>=61.0; extra == "dev"
Requires-Dist: wheel; extra == "dev"
Requires-Dist: twine; extra == "dev"
Dynamic: author
Dynamic: author-email
Dynamic: classifier
Dynamic: license-file
Dynamic: provides-extra
Dynamic: requires-dist
Dynamic: requires-python
Dynamic: summary
